input_sanitizer/__init__.py
input_sanitizer/config.py
input_sanitizer/sanitized_fields.py
input_sanitizer/sanitized_forms.py
input_sanitizer/sanitized_models.py
input_sanitizer/sanitized_serializers.py
input_sanitizer/sanitizers.py
input_sanitizer-0.2.2.dist-info/LICENSE
input_sanitizer-0.2.2.dist-info/METADATA
input_sanitizer-0.2.2.dist-info/WHEEL
input_sanitizer-0.2.2.dist-info/top_level.txt
input_sanitizer-0.2.2.dist-info/RECORD
