Metadata-Version: 2.1
Name: input-sanitizer
Version: 0.2.2
Summary: Sanitizes input data to prevent XSS i.e. cross site scripting attacks.
Home-page: UNKNOWN
Author: Akshay Ghatul
Author-email: akshay.ghatul@trigensoft.com
License: MIT
Project-URL: Homepage, https://github.com/AkshayGhatul/input-sanitizer
Platform: UNKNOWN
License-File: LICENSE
Requires-Dist: bleach
